online_novel_downloader/__init__.py
online_novel_downloader/__main__.py
online_novel_downloader/main.py
online_novel_downloader-0.1.0.dist-info/METADATA
online_novel_downloader-0.1.0.dist-info/WHEEL
online_novel_downloader-0.1.0.dist-info/entry_points.txt
online_novel_downloader-0.1.0.dist-info/RECORD
